parsexml/__init__.py
parsexml-0.0.1.dist-info/LICENSE
parsexml-0.0.1.dist-info/METADATA
parsexml-0.0.1.dist-info/WHEEL
parsexml-0.0.1.dist-info/entry_points.txt
parsexml-0.0.1.dist-info/top_level.txt
parsexml-0.0.1.dist-info/RECORD
