Metadata-Version: 2.1
Name: parsexml
Version: 0.0.1
Summary: Simple XML parsing to python structure.
Home-page: https://github.com/alphabet5/parsexml
Author: John Burt
Author-email: 
License: UNKNOWN
Platform: UNKNOWN
Classifier: Programming Language :: Python :: 3
Classifier: License :: OSI Approved :: Apache Software License
Classifier: Operating System :: OS Independent
Requires-Python: >=3.6
